LICENSE
MANIFEST.in
README.md
setup.cfg
setup.py
django_mp_feedback.egg-info/PKG-INFO
django_mp_feedback.egg-info/SOURCES.txt
django_mp_feedback.egg-info/dependency_links.txt
django_mp_feedback.egg-info/top_level.txt
feedback/__init__.py
feedback/admin.py
feedback/forms.py
feedback/models.py
feedback/urls.py
feedback/views.py
feedback/locale/fr/LC_MESSAGES/django.mo
feedback/locale/fr/LC_MESSAGES/django.po
feedback/locale/nl/LC_MESSAGES/django.mo
feedback/locale/nl/LC_MESSAGES/django.po
feedback/locale/ru/LC_MESSAGES/django.mo
feedback/locale/ru/LC_MESSAGES/django.po
feedback/locale/uk/LC_MESSAGES/django.mo
feedback/locale/uk/LC_MESSAGES/django.po
feedback/migrations/0001_initial.py
feedback/migrations/__init__.py
feedback/static/feedback/feedback.js
feedback/static/feedback/feedback.min.js
feedback/templates/feedback/form-js.html
feedback/templates/feedback/form.html
feedback/templates/feedback/modal-js.html
feedback/templates/feedback/modal.html
feedback/templates/feedback/sms.txt
feedback/templates/feedback/success-message.html
feedback/templates/feedback/view.html
feedback/templates/feedback/email/message.html
feedback/templates/feedback/email/subject.txt
feedback/templatetags/__init__.py
feedback/templatetags/feedback.py