Metadata-Version: 1.1
Name: django-mp-feedback
Version: 0.1
Summary: Django feedback app
Home-page: https://github.com/pmaigutyak/mp-feedback
Author: Paul Maigutyak
Author-email: pmaigutyak@gmail.com
License: MIT
Download-URL: https://github.com/pmaigutyak/mp-feedback/archive/0.1.tar.gz
Platform: UNKNOWN
